MANIFEST.in
README.rst
requirements.txt
setup.py
test-requirements.txt
test/test_base_controller.py
test/test_base_management.py
test/test_status.py
tsmppt60_driver/__init__.py
tsmppt60_driver/base.py
tsmppt60_driver/status.py
tsmppt60_driver.egg-info/PKG-INFO
tsmppt60_driver.egg-info/SOURCES.txt
tsmppt60_driver.egg-info/dependency_links.txt
tsmppt60_driver.egg-info/requires.txt
tsmppt60_driver.egg-info/top_level.txt