Metadata-Version: 1.1
Name: tsmppt60-driver
Version: 0.2.0
Summary: Python module to get status of your solar charge controller TS-MPPT-60.
Home-page: https://github.com/dodo5522/tsmppt60_driver
Author: Takashi Ando
Author-email: takashi7ando@gmail.com
License: GPLv2
Platform: UNKNOWN
Classifier: Development Status :: 4 - Beta
Classifier: Environment :: Console
Classifier: License :: OSI Approved :: GNU General Public License v2 (GPLv2)
Classifier: Natural Language :: English
Classifier: Programming Language :: Python :: 3.5
Classifier: Programming Language :: Python :: 3.6
Classifier: Programming Language :: Python :: 3.7
Classifier: Programming Language :: Python :: 3.8
Classifier: Programming Language :: Python :: 3.9
Classifier: Topic :: System :: Hardware :: Hardware Drivers
